Metadata-Version: 2.1
Name: declensions
Version: 0.1
Summary: Declension of words from the languages depending on the count.
Home-page: UNKNOWN
Author-email: beeeirym@gmail.com
License: UNKNOWN
Platform: UNKNOWN
